lyrichroma/__init__.py
lyrichroma/main.py
lyrichroma/renderer.py
lyrichroma/transcriber.py
lyrichroma/types.py
lyrichroma/asr/__init__.py
lyrichroma/asr/base.py
lyrichroma/asr/faster_whisper.py
lyrichroma-0.1.0.dist-info/METADATA
lyrichroma-0.1.0.dist-info/WHEEL
lyrichroma-0.1.0.dist-info/entry_points.txt
lyrichroma-0.1.0.dist-info/RECORD
