Metadata-Version: 2.4
Name: lyrichroma
Version: 0.1.0
Summary: Convert audio to video with auto-generated karaoke subtitles
Requires-Python: >=3.9
Requires-Dist: faster-whisper
Requires-Dist: moviepy>=2.0.0
Requires-Dist: numpy
Requires-Dist: pillow
